mensajes/__init__.py
mensajes/adios/__init__.py
mensajes/adios/desepedidas.py
mensajes/hola/__init__.py
mensajes/hola/saludos.py
mensajes_albiery-7.0.dist-info/licenses/LICENSE
tests/__init__.py
tests/test_hola.py
mensajes_albiery-7.0.dist-info/METADATA
mensajes_albiery-7.0.dist-info/WHEEL
mensajes_albiery-7.0.dist-info/top_level.txt
mensajes_albiery-7.0.dist-info/RECORD
